{
  "lists": [
    {
      "id": 1,
      "name": "For buying",
      "colorId": 6
    },
    {
      "id": 2,
      "name": "Vue",
      "colorId": 4
    },
    {
      "id": 3,
      "name": "Movie and serials",
      "colorId": 3
    },
    {
      "id": 4,
      "name": "Books",
      "colorId": 2
    },
    {
      "id": 5,
      "name": "Self",
      "colorId": 1
    },
    {
      "name": "hello",
      "colorId": 6,
      "id": 6
    },
    {
      "name": "new tasks",
      "colorId": 6,
      "id": 7
    },
    {
      "name": "qwe",
      "colorId": 2,
      "id": 8
    },
    {
      "name": "qq",
      "colorId": 2,
      "id": 9
    },
    {
      "name": "qwew",
      "colorId": 2,
      "id": 10
    }
  ],
  "tasks": [
    {
      "id": 1,
      "listId": 2,
      "text": "Learn Node js",
      "completed": false
    },
    {
      "id": 2,
      "listId": 2,
      "text": "Learn Patters",
      "completed": false
    },
    {
      "id": 3,
      "listId": 2,
      "text": "ReactJS Hooks (useState, useReducer, useEffect etc.)",
      "completed": true
    },
    {
      "id": 4,
      "listId": 2,
      "text": "Redux (redux-observable, redux-saga)",
      "completed": false
    },
    {
      "listId": 1,
      "text": "hello",
      "completed": false,
      "id": 6
    },
    {
      "listId": 6,
      "text": "hello",
      "completed": false,
      "id": 7
    }
  ],
  "colors": [
    {
      "id": 1,
      "hex": "#C9D1D3",
      "name": "gray"
    },
    {
      "id": 2,
      "hex": "#42B883",
      "name": "green"
    },
    {
      "id": 3,
      "hex": "#64C4ED",
      "name": "blue"
    },
    {
      "id": 4,
      "hex": "#FFBBCC",
      "name": "pink"
    },
    {
      "id": 5,
      "hex": "#B6E6BD",
      "name": "lime"
    },
    {
      "id": 6,
      "hex": "#C355F5",
      "name": "purple"
    },
    {
      "id": 7,
      "hex": "#110133",
      "name": "black"
    },
    {
      "id": 8,
      "hex": "#FF6464",
      "name": "red"
    }
  ]
}